{
  "$schema": "https://on.cypress.io/cypress.schema.json",
  "watchForFileChanges": false,
  "chromeWebSecurity": false,
  "baseUrl": "https://opensource-demo.orangehrmlive.com/index.php/auth/login",
  "pageLoadTimeout": 90000,
  "requestTimeout": 5000,
  "responseTimeout": 30000,
  "defaultCommandTimeout": 30000,
  "videoUploadOnPasses": false,
  "screenshotOnRunFailure": true,
  "reporter": "cypress-dashboard",
  "reporterOptions": {
    "reportDir": "cypress/DashBoardReports",
    "isLocalDeployment": true
  }
}